LICENSE
MANIFEST.in
README.rst
setup.cfg
setup.py
docs/Makefile
docs/conf.py
docs/configuration.rst
docs/development.rst
docs/disable_with_comments.rst
docs/index.rst
docs/quickstart.rst
docs/rules.rst
docs/screenshot.png
docs/text_editors.rst
extended_yamllint.egg-info/PKG-INFO
extended_yamllint.egg-info/SOURCES.txt
extended_yamllint.egg-info/dependency_links.txt
extended_yamllint.egg-info/entry_points.txt
extended_yamllint.egg-info/requires.txt
extended_yamllint.egg-info/top_level.txt
yamllint/__init__.py
yamllint/cli.py
yamllint/config.py
yamllint/linter.py
yamllint/parser.py
yamllint/conf/default.yaml
yamllint/conf/relaxed.yaml
yamllint/rules/Matcher.py
yamllint/rules/__init__.py
yamllint/rules/braces.py
yamllint/rules/brackets.py
yamllint/rules/colons.py
yamllint/rules/commas.py
yamllint/rules/comments.py
yamllint/rules/comments_indentation.py
yamllint/rules/common.py
yamllint/rules/document_end.py
yamllint/rules/document_start.py
yamllint/rules/empty_lines.py
yamllint/rules/hardcoded.py
yamllint/rules/hyphens.py
yamllint/rules/indentation.py
yamllint/rules/key_duplicates.py
yamllint/rules/line_length.py
yamllint/rules/new_line_at_end_of_file.py
yamllint/rules/new_lines.py
yamllint/rules/trailing_spaces.py
yamllint/rules/truthy.py