Metadata-Version: 1.1
Name: extended-yamllint
Version: 0.2
Summary: A linter for YAML files.
Home-page: https://github.com/aprasolova/yamllint
Author: aprasolova
Author-email: anastasia.prasolova@emc.com
License: GPLv3
Keywords: yaml,lint,linter,syntax,checker
Platform: UNKNOWN
Classifier: Development Status :: 5 - Production/Stable
Classifier: Environment :: Console
Classifier: Intended Audience :: Developers
Classifier: License :: OSI Approved :: GNU General Public License v3 (GPLv3)
Classifier: Programming Language :: Python :: 2
Classifier: Programming Language :: Python :: 3
Classifier: Topic :: Software Development
Classifier: Topic :: Software Development :: Debuggers
Classifier: Topic :: Software Development :: Quality Assurance
Classifier: Topic :: Software Development :: Testing
